fmc_client/__init__.py
fmc_client/api_client.py
fmc_client/configuration.py
fmc_client/rest.py
fmc_client/api/__init__.py
fmc_client/api/audit_api.py
fmc_client/api/deployment_api.py
fmc_client/api/device_clusters_api.py
fmc_client/api/device_groups_api.py
fmc_client/api/device_ha_pairs_api.py
fmc_client/api/devices_api.py
fmc_client/api/health_api.py
fmc_client/api/integration_api.py
fmc_client/api/intelligence_api.py
fmc_client/api/object_api.py
fmc_client/api/policy_api.py
fmc_client/api/policy_assignments_api.py
fmc_client/api/status_api.py
fmc_client/api/system_information_api.py
fmc_client/api/updates_api.py
fmc_client/api/users_api.py
fmc_client/models/__init__.py
fmc_client/models/access_policy.py
fmc_client/models/access_policy_category.py
fmc_client/models/access_policy_category_list_container.py
fmc_client/models/access_policy_category_metadata.py
fmc_client/models/access_policy_inheritance_setting.py
fmc_client/models/access_policy_inheritance_setting_list_container.py
fmc_client/models/access_policy_list_container.py
fmc_client/models/access_policy_logging_setting_model.py
fmc_client/models/access_policy_logging_setting_model_list_container.py
fmc_client/models/access_rule.py
fmc_client/models/access_rule_list_container.py
fmc_client/models/access_rule_metadata.py
fmc_client/models/any_protocol_port_object.py
fmc_client/models/any_protocol_port_object_list_container.py
fmc_client/models/applicable_device.py
fmc_client/models/applicable_device_list_container.py
fmc_client/models/application.py
fmc_client/models/application_category.py
fmc_client/models/application_category_list_container.py
fmc_client/models/application_filter.py
fmc_client/models/application_filter_list_container.py
fmc_client/models/application_list_container.py
fmc_client/models/application_productivity.py
fmc_client/models/application_productivity_list_container.py
fmc_client/models/application_risk.py
fmc_client/models/application_risk_list_container.py
fmc_client-1.0.0.dist-info/METADATA
fmc_client-1.0.0.dist-info/WHEEL
fmc_client-1.0.0.dist-info/top_level.txt
fmc_client-1.0.0.dist-info/RECORD
